LICENSE
MANIFEST.in
README.md
setup.cfg
setup.py
aldryn_newsblog_extra_plugins/__init__.py
aldryn_newsblog_extra_plugins/cms_plugins.py
aldryn_newsblog_extra_plugins/forms.py
aldryn_newsblog_extra_plugins/models.py
aldryn_newsblog_extra_plugins/utils.py
aldryn_newsblog_extra_plugins.egg-info/PKG-INFO
aldryn_newsblog_extra_plugins.egg-info/SOURCES.txt
aldryn_newsblog_extra_plugins.egg-info/dependency_links.txt
aldryn_newsblog_extra_plugins.egg-info/not-zip-safe
aldryn_newsblog_extra_plugins.egg-info/requires.txt
aldryn_newsblog_extra_plugins.egg-info/top_level.txt
aldryn_newsblog_extra_plugins/migrations/0001_initial.py
aldryn_newsblog_extra_plugins/migrations/0002_auto_20170711_1104.py
aldryn_newsblog_extra_plugins/migrations/0003_auto_20170924_0958.py
aldryn_newsblog_extra_plugins/migrations/0004_newsbloglatestarticlesbycategoryplugin.py
aldryn_newsblog_extra_plugins/migrations/0005_auto_20190520_1411.py
aldryn_newsblog_extra_plugins/migrations/__init__.py
aldryn_newsblog_extra_plugins/templates/aldryn_newsblog/plugins/latest_articles_by_category.html
aldryn_newsblog_extra_plugins/templates/aldryn_newsblog/plugins/tagged_articles.html