Metadata-Version: 2.1
Name: aldryn-newsblog-extra-plugins
Version: 0.2.0
Summary: Extra plugins for aldryn-newsblog.
Home-page: https://github.com/febsn/aldryn-newsblog-extra-plugins
Author: Fabian Lehner
Author-email: fabian.lehner@marmara.at
License: MIT
Platform: OS Independent
Classifier: Development Status :: 3 - Alpha
Classifier: Environment :: Web Environment
Classifier: Framework :: Django
Classifier: License :: OSI Approved :: MIT License
Classifier: Operating System :: OS Independent
Classifier: Programming Language :: Python
Classifier: Topic :: Internet :: WWW/HTTP :: Dynamic Content
Classifier: Programming Language :: Python
